anticor_features/__init__.py
anticor_features/anticor_features.py
anticor_features/anticor_stats.py
anticor_features-0.2.3.dist-info/METADATA
anticor_features-0.2.3.dist-info/WHEEL
anticor_features-0.2.3.dist-info/top_level.txt
anticor_features-0.2.3.dist-info/RECORD
