Metadata-Version: 2.1
Name: anticor-features
Version: 0.2.3
Summary: Anti-correlation based feature selection for single cell datasets
Home-page: https://scottyler892@bitbucket.org/scottyler892/anticor_features
Author: Scott Tyler
Author-email: scottyler89@gmail.com
Classifier: Programming Language :: Python :: 3
Classifier: License :: OSI Approved :: GNU Affero General Public License v3
Classifier: Operating System :: OS Independent
Requires-Dist: h5py
Requires-Dist: numpy
Requires-Dist: pandas
Requires-Dist: seaborn
Requires-Dist: matplotlib
Requires-Dist: scipy
Requires-Dist: numba
Requires-Dist: ray
Requires-Dist: gprofiler-official (==0.3.5)
Requires-Dist: psutil
